prawscripts/__init__.py
prawscripts/antibrigadingbanbot.py
prawscripts/checkbanstatus.py
prawscripts/checkcrosspostperms.py
prawscripts/checkprivate.py
prawscripts/checksharedsubs.py
prawscripts/checksubperms.py
prawscripts/getinstance.py
prawscripts/getmodmailcount.py
prawscripts/removefromdeleted.py
prawscripts/searchmessageinboxkeyword.py
prawscripts/searchnewestpost.py
prawscripts/widgetbuilder.py
prawscripts-0.0.9.dist-info/METADATA
prawscripts-0.0.9.dist-info/WHEEL
prawscripts-0.0.9.dist-info/top_level.txt
prawscripts-0.0.9.dist-info/RECORD
